odoo/addons/l10n_th_base_location/README.rst
odoo/addons/l10n_th_base_location/__init__.py
odoo/addons/l10n_th_base_location/__manifest__.py
odoo/addons/l10n_th_base_location/data/TH_en.txt
odoo/addons/l10n_th_base_location/data/TH_th.txt
odoo/addons/l10n_th_base_location/demo/TH_en.txt
odoo/addons/l10n_th_base_location/demo/TH_th.txt
odoo/addons/l10n_th_base_location/i18n/base_location_thailand.pot
odoo/addons/l10n_th_base_location/i18n/l10n_th_base_location.pot
odoo/addons/l10n_th_base_location/i18n/th.po
odoo/addons/l10n_th_base_location/models/__init__.py
odoo/addons/l10n_th_base_location/models/res_city_zip.py
odoo/addons/l10n_th_base_location/models/res_company.py
odoo/addons/l10n_th_base_location/models/res_country_state.py
odoo/addons/l10n_th_base_location/models/res_partner.py
odoo/addons/l10n_th_base_location/readme/CONTRIBUTORS.rst
odoo/addons/l10n_th_base_location/readme/CREDITS.rst
odoo/addons/l10n_th_base_location/readme/DESCRIPTION.rst
odoo/addons/l10n_th_base_location/readme/INSTALL.rst
odoo/addons/l10n_th_base_location/readme/USAGE.rst
odoo/addons/l10n_th_base_location/static/description/icon.png
odoo/addons/l10n_th_base_location/static/description/index.html
odoo/addons/l10n_th_base_location/tests/__init__.py
odoo/addons/l10n_th_base_location/tests/test_base_location.py
odoo/addons/l10n_th_base_location/views/res_city_zip_view.xml
odoo/addons/l10n_th_base_location/wizard/__init__.py
odoo/addons/l10n_th_base_location/wizard/geonames_import.py
odoo/addons/l10n_th_base_location/wizard/geonames_import_view.xml
odoo14_addon_l10n_th_base_location-14.0.1.0.1.dev5.dist-info/METADATA
odoo14_addon_l10n_th_base_location-14.0.1.0.1.dev5.dist-info/WHEEL
odoo14_addon_l10n_th_base_location-14.0.1.0.1.dev5.dist-info/top_level.txt
odoo14_addon_l10n_th_base_location-14.0.1.0.1.dev5.dist-info/RECORD
